odoo/addons/stock_inventory_exclude_sublocation/README.rst
odoo/addons/stock_inventory_exclude_sublocation/__init__.py
odoo/addons/stock_inventory_exclude_sublocation/__manifest__.py
odoo/addons/stock_inventory_exclude_sublocation/i18n/cs_CZ.po
odoo/addons/stock_inventory_exclude_sublocation/i18n/de.po
odoo/addons/stock_inventory_exclude_sublocation/i18n/es.po
odoo/addons/stock_inventory_exclude_sublocation/i18n/es_ES.po
odoo/addons/stock_inventory_exclude_sublocation/i18n/fr.po
odoo/addons/stock_inventory_exclude_sublocation/i18n/it.po
odoo/addons/stock_inventory_exclude_sublocation/i18n/pt_BR.po
odoo/addons/stock_inventory_exclude_sublocation/i18n/sl.po
odoo/addons/stock_inventory_exclude_sublocation/i18n/stock_inventory_exclude_sublocation.pot
odoo/addons/stock_inventory_exclude_sublocation/i18n/zh_CN.po
odoo/addons/stock_inventory_exclude_sublocation/models/__init__.py
odoo/addons/stock_inventory_exclude_sublocation/models/stock_inventory.py
odoo/addons/stock_inventory_exclude_sublocation/readme/CONTRIBUTORS.rst
odoo/addons/stock_inventory_exclude_sublocation/readme/DESCRIPTION.rst
odoo/addons/stock_inventory_exclude_sublocation/readme/USAGE.rst
odoo/addons/stock_inventory_exclude_sublocation/static/description/icon.png
odoo/addons/stock_inventory_exclude_sublocation/static/description/index.html
odoo/addons/stock_inventory_exclude_sublocation/tests/__init__.py
odoo/addons/stock_inventory_exclude_sublocation/tests/test_exclude_sublocation.py
odoo/addons/stock_inventory_exclude_sublocation/views/stock_inventory_view.xml
odoo12_addon_stock_inventory_exclude_sublocation-12.0.1.0.1.dist-info/METADATA
odoo12_addon_stock_inventory_exclude_sublocation-12.0.1.0.1.dist-info/WHEEL
odoo12_addon_stock_inventory_exclude_sublocation-12.0.1.0.1.dist-info/top_level.txt
odoo12_addon_stock_inventory_exclude_sublocation-12.0.1.0.1.dist-info/RECORD
